sranodec/__init__.py
sranodec/silency.py
sranodec/util.py
tests/__init__.py
tests/test_silency.py
tests/mock/__init__.py
tests/mock/srdata.py
sranodec-0.0.1.dist-info/LICENSE
sranodec-0.0.1.dist-info/METADATA
sranodec-0.0.1.dist-info/WHEEL
sranodec-0.0.1.dist-info/top_level.txt
sranodec-0.0.1.dist-info/RECORD
