Metadata-Version: 2.1
Name: sranodec
Version: 0.0.1
Summary: Anonmaly Detection by Spectral Residual
Home-page: https://github.com/y-bar/spectral-residual
Maintainer: Takahiro Yoshinaga
Maintainer-email: t.yoshinaga0106@gmail.com
License: MIT
Platform: UNKNOWN
Requires-Dist: matplotlib
Requires-Dist: numpy
Requires-Dist: scipy
